{
  "events": [
    {
      "id": "k0kshgjhkk7jgek0oorcu6m8fs_20260421",
      "summary": "Pipeline Meeting",
      "start": "2026-04-21T10:30:00-07:00",
      "end": "2026-04-21T11:30:00-07:00",
      "acct": "chance@360suitesla.com"
    },
    {
      "id": "i5gapi82ctc4g9bs2tg05l02s7_20260421",
      "summary": "Loan Bro Meeting",
      "start": "2026-04-21T11:00:00-07:00",
      "end": "2026-04-21T11:30:00-07:00",
      "acct": "chance@360suitesla.com"
    }
  ],
  "synced_at": "2026-04-15T06:00:00Z",
  "source": "google_calendar_mcp"
}
